lexa_sdk/README.md
lexa_sdk/__init__.py
lexa_sdk/client.py
lexa_sdk/exceptions.py
lexa_sdk/language_model.py
lexa_sdk/models.py
lexa_sdk/provider.py
lexa_sdk/pyproject.toml
lexa_sdk/ssl_config.py
lexa_sdk/ssl_enhancer.py
lexa-1.0.3.dist-info/METADATA
lexa-1.0.3.dist-info/WHEEL
lexa-1.0.3.dist-info/licenses/LICENSE
lexa-1.0.3.dist-info/RECORD
