Metadata-Version: 2.4
Name: lexa
Version: 1.0.3
Summary: Python SDK for Lexa AI - OpenAI-compatible interface for Lexa's language models
Project-URL: Homepage, https://lexa.chat
Project-URL: Repository, https://github.com/Robi-Labs/lexa-python-sdk
Project-URL: Documentation, https://docs.lexa.chat/
Project-URL: Bug Tracker, https://github.com/Robi-Labs/lexa-python-sdk/issues
Author-email: Robi Labs <lexa@robiai.com>
License: MIT
License-File: LICENSE
Keywords: ai,api,chat,completion,lexa,llm,ml
Classifier: Development Status :: 5 - Production/Stable
Classifier: Intended Audience :: Developers
Classifier: License :: OSI Approved :: MIT License
Classifier: Programming Language :: Python :: 3
Classifier: Programming Language :: Python :: 3.8
Classifier: Programming Language :: Python :: 3.9
Classifier: Programming Language :: Python :: 3.10
Classifier: Programming Language :: Python :: 3.11
Classifier: Programming Language :: Python :: 3.12
Classifier: Topic :: Scientific/Engineering :: Artificial Intelligence
Classifier: Topic :: Software Development :: Libraries :: Python Modules
Requires-Python: >=3.8
Requires-Dist: httpx>=0.24.0
Requires-Dist: pydantic>=2.0.0
Requires-Dist: requests>=2.25.0
Requires-Dist: typing-extensions>=4.0.0
